Metadata-Version: 2.1
Name: tradingview
Version: 0.0.2
Summary: Library For TradingView
Home-page: UNKNOWN
Author: Kanta Kuramoto
Author-email: kanta208@gmail.com
License: UNKNOWN
Platform: UNKNOWN
Classifier: Development Status :: 1 - Planning
Classifier: License :: OSI Approved :: MIT License
Classifier: Programming Language :: Python :: 3.7
Classifier: Programming Language :: Python :: 3.8
Classifier: Programming Language :: Python :: 3.9
